{"1157529280": {"海德": 95, "罗杰": 21, "安洁莉亚": 29, "古鲁瓦德": 34, "庞": 16, "卡努拉": 17, "库尔": 29, "蠢熊勇士": 10, "迪兰": 16, "尼德": 23, "琉": 15, "刃": 22, "猫眼": 20, "米兰达": 5, "纳杰尔": 15, "艾利欧": 40, "娜雅": 24, "蒂卡": 19, "法蒂玛": 24, "普吉": 26, "尧": 15, "实验体": 10, "玛莉亚": 10, "诺瓦": 60, "芈芈": 10, "荷丝缇雅": 25, "卡莲": 25, "迪兰SP": 100, "琼安": 10, "希欧": 10, "勇铉": 5, "卷云": 10, "琼安SP": 50, "克拉克": 60, "奥斯塔": 15, "杰罗姆": 40, "千雪": 25, "米莎": 85, "吉哈萨哈": 10, "庞SP": 50, "夏尔": 5, "艾斯": 30, "扬波": 20, "泉": 25, "贝雅塔": 5, "黯月SP": 50, "雷萨": 75, "爱丽丝": 20, "雪尔森": 10, "澪": 0, "Deemo": 50, "Emma": 0, "魂乐": 150, "橘籽": 350, "月色": 150, "起司猫": 150, "七画": 50, "月舞之剑": 100, "Twip": 0, "鳄鱼": 100, "夹心酱": 100, "板蓝根": 50, "皮卡丘": 50, "北洛": 50, "哦豁": 50, "暗能量": 50, "透明": 50, "多冰奶茶": 0, "秀贤": 5, "匆匆": 100, "洛": 5, "卢恩": 5, "黯月": 40, "雪莉": 50, "丽莎": 20, "汀朵伊姆": 40, "芙蕾莉卡": 20, "莫里斯": 20, "紫苑": 100, "魔王艾玛": 100, "魔王伊丽莎白": 150, "缇": 100, "万象乐舞": 100, "芙洛莱": 150, "魔王莉莉丝": 50, "魔王弗洛里亚": 50, "魔王贝丽卡": 50, "魔王穆里尔": 150}, "1355649540": {"七画": 0, "起司猫": 50, "板蓝根": 0, "橘籽": 50, "魂乐": 100, "Emma": 0, "哦豁": 0}, "2649079653": {"猫眼": 2, "尼德": 1, "库尔": 1, "法蒂玛": 1, "蒂卡": 1, "古鲁瓦德": 2, "卡努拉": 1, "安洁莉亚": 1}, "1007765793": {"尼德": 7, "庞": 6, "库尔": 8, "海德": 5, "莫里斯": 60, "璃": 10, "娜雅": 11, "卡努拉": 7, "猫眼": 12, "荷丝缇雅": 10, "蒂卡": 7, "玛莉亚": 45, "刃": 8, "爱丽丝": 5, "碎牙": 10, "安洁莉亚": 9, "千雪": 5, "罗杰": 5, "古鲁瓦德": 12, "画境哦豁": 50, "迪兰": 7, "雪莉": 25, "苏菲": 40, "画境阿征": 50, "贝希莫斯": 50, "普吉": 6, "博丽灵梦": 100, "杰罗姆": 20, "法蒂玛": 5, "西奥多": 5, "艾利欧": 10, "夏洛克": 5, "芙蕾莉卡": 20, "黛安娜": 20, "扬波": 5, "万象橘籽": 50, "丽莎": 20, "夏尔": 5, "画境月舞": 50, "暗能量": 50, "琼安": 5, "泉": 20, "芈芈": 5, "雷萨": 20, "画境月色": 50}, "2691211800": {"庞": 3, "海德": 50, "普吉": 10, "迪兰": 6, "尼德": 10, "古鲁瓦德": 9, "罗杰": 7, "蒂卡": 3, "荷丝缇雅": 4, "黛安娜": 20, "雪尔森MZ": 50, "安洁莉亚": 5, "库尔": 11, "卡莲": 5, "娜雅": 4, "杰罗姆": 25, "猫眼": 9, "卡努拉": 6, "爱丽丝": 5, "刃": 4, "雪尔森": 5, "实验体": 5, "法蒂玛": 3, "尧": 10, "希欧MZ": 50, "洛": 5, "琼安": 20, "泉": 5, "雷萨": 10, "甲申": 5, "吉哈萨哈": 5, "苏菲": 5, "琼安MZ": 50, "泉MZ": 50, "娜雅MZ": 50}, "410937091": {"海德": 25, "卡努拉": 30, "荷丝缇雅": 25, "卷云": 10, "蒂卡": 34, "安洁莉亚": 23, "庞": 27, "雷萨": 50, "刃": 28, "古鲁瓦德": 36, "艾斯": 50, "爱丽丝": 75, "罗杰": 18, "普吉": 38, "梨花": 40, "尼德": 31, "迪兰": 26, "杰罗姆": 15, "库尔": 26, "琉SP": 50, "卢恩": 20, "猫眼": 44, "丽莎": 40, "艾利欧": 25, "克拉克": 50, "法蒂玛": 26, "娜雅": 34, "纳杰尔": 10, "法蒂玛SP": 50, "希欧SP": 50, "夏尔SP": 50, "玛莉亚SP": 50, "丽莎SP": 50, "黛安娜": 80, "卡莲": 50, "雅辛托斯SP": 50, "洛SP": 50, "苏菲": 45, "黯月": 20, "璃": 70, "芈芈": 30, "雷萨SP": 100, "秀贤": 20, "扬波": 5, "雪莉SP": 50, "杰罗姆MZ": 50, "碎牙": 10, "希欧": 5, "画境哦豁": 50, "泉": 5, "琼安": 25, "雪尔森": 20, "安洁莉亚MZ": 50, "板蓝根": 50, "洛": 10, "万象筱林": 50, "娜雅MZ": 50, "夏洛克": 5, "米兰达": 30, "夏尔": 10, "玛莉亚": 50, "纳杰尔SP": 50, "千雪": 10, "莫里斯": 40, "甲申": 10, "PAFF": 50, "画境月色": 50, "奥斯塔": 5, "NEKO": 50, "汀朵伊姆": 40, "米莎": 20, "实验体": 5, "画境阿征": 50}, "189322529": {"刃": 3, "法蒂玛": 1, "古鲁瓦德": 8, "安洁莉亚": 2, "普吉": 3, "千雪": 5, "庞": 2, "罗杰": 2, "库尔": 3, "娜雅": 2, "荷丝缇雅": 1, "迪兰": 6, "蒂卡": 3, "尼德": 1, "蚯蚓肉丸": 50, "猫眼": 1}, "1598049455": {"罗杰": 10, "安洁莉亚": 8, "卡努拉": 4, "尼德": 4, "法蒂玛": 2, "普吉": 4, "猫眼": 8, "蒂卡": 6, "庞": 3, "刃": 4, "库尔": 4, "娜雅": 5, "迪兰": 6, "荷丝缇雅": 7, "艾斯": 20, "米兰达": 5, "玛莉亚": 5, "雷萨": 5, "艾利欧": 25, "千雪": 5, "古鲁瓦德": 5, "汀朵伊姆": 20, "夏尔": 5, "琉": 5}, "1510656400": {"泉": 35, "荷丝缇雅SP": 100, "罗杰": 58, "安洁莉亚": 56, "猫眼": 46, "庞": 50, "尼德": 53, "璃": 45, "卡努拉": 43, "碎牙": 30, "库尔": 44, "古鲁瓦德": 49, "蠢熊勇士": 15, "娜雅": 64, "蒂卡": 52, "艾利欧": 115, "雪莉SP": 100, "法蒂玛": 51, "荷丝缇雅": 54, "莫里斯": 40, "普吉": 55, "苏菲SP": 50, "夏尔": 20, "尧": 10, "刃": 54, "迪兰": 57, "雷萨": 85, "秀贤": 25, "夏洛克": 10, "卡莲": 45, "NEKO": 50, "汀朵伊姆": 30, "Deemo": 150, "西奥多": 10, "雪尔森": 125, "汀朵伊姆MZ": 50, "黛安娜MZ": 50, "吉哈萨哈": 25, "雪尔森MZ": 50, "苏菲": 50, "玛莉亚": 150, "琉": 5, "琼安": 75, "普吉SP": 100, "米莎": 50, "实验体": 10, "艾斯": 30, "雪莉": 55, "扬波": 20, "Nora": 50, "克拉克": 55, "诺瓦SP": 50, "梨花": 40, "贝雅塔": 20, "千雪": 45, "诺瓦": 25, "希欧SP": 100, "海德": 30, "迪兰SP": 50, "杰罗姆": 55, "卢恩": 25, "纳杰尔": 20, "庞SP": 50, "黯月SP": 100, "米兰达": 85, "爱丽丝": 110, "米兰达SP": 50, "卷云": 20, "罗杰SP": 100, "黛安娜": 50, "芙蕾莉卡SP": 100, "杰罗姆SP": 100, "芈芈": 45, "蒂卡SP": 50, "丽莎": 40, "Ivy": 100, "洛SP": 50, "纳杰尔SP": 100, "奥斯塔": 5, "米兰达MZ": 100, "泉MZ": 50, "洛": 5, "黯月MZ": 100, "芙蕾莉卡": 20, "夏尔SP": 50, "希欧": 5}, "2529183817": {"古鲁瓦德": 2, "迪兰": 1, "尼德": 1, "庞": 1, "法蒂玛": 1, "蒂卡": 1, "琼安": 5, "猫眼": 1, "库尔": 1}, "3110466373": {"安洁莉亚": 17, "普吉": 15, "法蒂玛": 22, "古鲁瓦德": 23, "安洁莉亚SP": 50, "罗杰": 12, "刃": 15, "克拉克": 5, "贝雅塔": 10, "荷丝缇雅": 25, "库尔": 18, "秀贤": 5, "琉": 5, "卡努拉": 18, "艾斯": 45, "猫眼": 16, "芙蕾莉卡": 40, "娜雅": 15, "爱丽丝": 70, "迪兰": 18, "丽莎": 60, "米莎": 20, "黛安娜": 50, "夏洛克": 5, "璃": 25, "尼德": 23, "蒂卡": 15, "雪莉": 5, "皮皮鳄鱼": 50, "庞": 10, "海德": 5, "万象橘籽": 50, "万象燃灯": 50, "玛莉亚": 5, "画境艾玛": 50, "甲申": 15, "吉哈萨哈": 5, "雷萨": 20, "千雪": 25, "艾利欧": 10, "万象魂乐": 100, "泉": 40, "卡莲": 5, "画师咕咕": 50, "尧": 5, "扬波": 5, "画境阿征": 50, "杰罗姆": 5, "奥斯塔": 5, "汀朵伊姆": 5, "卷云": 5, "苏菲": 5, "洛": 5}, "2115006958": {"荷丝缇雅": 3, "尼德": 5, "罗杰": 4, "万象北落": 50, "安洁莉亚": 2, "蒂卡": 5, "库尔": 9, "迪兰": 3, "法蒂玛": 4, "古鲁瓦德": 4, "艾斯": 5, "庞": 1, "万象夹心": 50, "夏洛克": 5, "苏菲": 5, "娜雅": 3, "猫眼": 3, "爱丽丝": 5, "卡努拉": 2, "多冰奶茶": 0, "卡莲": 20, "刃": 1, "卢恩": 5, "普吉": 1, "海德": 5}, "2644954866": {"庞": 2, "库尔": 5, "纳杰尔": 5, "蒂卡": 1, "安洁莉亚": 1, "卡努拉": 2, "法蒂玛": 1, "荷丝缇雅": 1, "古鲁瓦德": 1, "罗杰": 1, "刃": 2, "爱丽丝": 20, "实验体": 5}, "1736682010": {"爱丽丝": 5, "迪兰": 1, "猫眼": 1, "普吉": 2, "琼安": 5, "娜雅": 2, "荷丝缇雅": 3, "安洁莉亚": 2, "古鲁瓦德": 1, "库尔": 1, "雪莉": 20, "刃": 1, "法蒂玛": 2, "罗杰": 1}, "985234443": {"罗杰": 1, "庞": 1, "安洁莉亚": 2, "法蒂玛": 1, "古鲁瓦德": 1, "蒂卡": 1, "荷丝缇雅": 1, "娜雅": 1, "苏菲": 5}, "2012834529": {"普吉": 4, "安洁莉亚": 1, "尼德": 4, "米兰达": 25, "猫眼": 4, "罗杰": 6, "荷丝缇雅": 3, "库尔": 4, "米莎": 5, "娜雅": 5, "庞": 2, "古鲁瓦德": 3, "蒂卡": 2, "法蒂玛": 4, "诺瓦": 20, "卡努拉": 2, "梨花": 20, "刃": 1, "迪兰": 1, "玛莉亚": 5, "艾利欧": 5, "杰罗姆": 5, "荷丝缇雅SP": 50, "丽莎SP": 50, "琉": 15, "雪尔森": 5}, "1530518175": {"蒂卡": 2, "米莎": 20, "艾斯": 20, "诺瓦": 20, "荷丝缇雅": 1, "罗杰": 1, "迪兰": 1, "法蒂玛": 1, "卡努拉": 1}, "979971498": {"罗杰": 11, "璃": 35, "米兰达SP": 100, "猫眼": 21, "夏洛克": 5, "刃": 24, "卡努拉": 25, "雪莉": 10, "普吉": 21, "娜雅": 21, "安洁莉亚": 13, "卢恩": 5, "蒂卡": 26, "古鲁瓦德": 21, "尼德": 23, "琼安": 30, "荷丝缇雅": 11, "库尔": 13, "秀贤": 5, "希欧": 5, "法蒂玛": 16, "迪兰": 22, "庞": 15, "黛安娜": 10, "诺瓦": 50, "爱丽丝": 10, "勇铉": 5, "璃SP": 50, "艾利欧": 5, "米兰达": 15, "芈芈": 45, "泉SP": 100, "艾利欧SP": 50, "夏尔": 10, "扬波": 5, "普吉SP": 50, "米莎": 25, "实验体": 15, "洛": 10, "千雪": 50, "夏洛克SP": 50, "汀朵伊姆": 30, "梨花": 50, "奥斯塔": 5, "雷萨": 10, "克拉克": 45, "雪尔森": 5, "芙蕾莉卡SP": 50, "尧": 10, "泉": 5, "海德": 30, "贝雅塔": 10, "西奥多": 5, "艾斯": 25, "夏尔SP": 50, "杰罗姆": 5, "苏菲SP": 100, "卡莲": 5, "迪兰SP": 50, "丽莎SP": 50, "雪尔森SP": 50, "莫里斯": 20, "雪莉MZ": 50, "苏菲": 20, "黛安娜MZ": 50, "杰罗姆MZ": 50}, "2752143239": {"安洁莉亚": 1, "猫眼": 3, "庞": 3, "普吉": 1, "古鲁瓦德": 1, "荷丝缇雅": 1}, "515752618": {"泉": 5, "蒂卡": 1, "荷丝缇雅": 1, "法蒂玛": 2, "猫眼": 1, "安洁莉亚": 1, "罗杰": 1, "克拉克": 5, "庞": 1}, "1440734330": {"实验体": 5, "荷丝缇雅": 1, "法蒂玛": 1, "安洁莉亚": 1, "卡努拉": 1, "卢恩": 5, "刃": 1, "迪兰": 1, "猫眼": 1, "黛安娜": 5}, "1933583359": {"古鲁瓦德": 3, "法蒂玛": 3, "汀朵伊姆": 5, "诺瓦": 5, "普吉": 4, "猫眼": 4, "安洁莉亚": 1, "迪兰": 2, "罗杰": 1, "尼德": 3, "荷丝缇雅": 3, "蒂卡": 2, "库尔": 2, "芈芈": 5, "暗能量": 50, "千雪": 20, "夏尔": 5, "娜雅": 1, "庞": 1, "艾斯": 5, "刃": 1, "莫里斯": 20, "璃MZ": 50}, "1264434864": {"卡努拉": 1, "庞": 1, "蒂卡": 1, "杰罗姆": 5, "尼德": 1, "娜雅": 1, "迪兰": 1, "法蒂玛": 1, "库尔": 1, "海德": 5}, "2135379565": {"蒂卡": 1, "荷丝缇雅": 1, "画境匆匆": 50, "安洁莉亚": 2, "迪兰": 1, "古鲁瓦德": 2, "刃": 1, "法蒂玛": 1}, "787616004": {"娜雅": 2, "普吉": 1, "迪兰": 3, "罗杰": 1, "蒂卡": 3, "猫眼": 1, "卡努拉": 1, "库尔": 1, "法蒂玛": 3, "甲申": 5, "尼德": 1, "庞": 1, "纳杰尔": 5}, "2837535623": {"庞": 1, "古鲁瓦德": 2, "普吉": 3, "尼德": 1, "法蒂玛": 4, "安洁莉亚": 3, "罗杰": 2, "娜雅": 1, "库尔": 1, "汀朵伊姆MZ": 50, "黛安娜MZ": 50}, "1136720084": {"古鲁瓦德": 3, "猫眼": 4, "法蒂玛": 1, "梨花": 20, "荷丝缇雅": 4, "安洁莉亚": 1, "卡莲": 5, "娜雅": 2, "玛莉亚": 5, "庞": 1, "尧": 5, "黛安娜": 20, "卡努拉": 1, "蒂卡": 1, "罗杰": 1, "千雪": 20, "卷云": 5, "普吉": 1, "迪兰": 1, "库尔": 1, "尼德": 1}, "2337275573": {"艾斯": 40, "蒂卡": 1, "苏菲": 20, "黯月": 40, "庞": 4, "吉哈萨哈": 5, "扬波": 5, "安洁莉亚": 1, "尼德": 1, "卡莲": 20, "雪尔森": 20, "普吉": 1, "罗杰": 1, "卡努拉": 1, "法蒂玛": 1, "洛": 5, "刃": 1, "琼安": 5, "荷丝缇雅": 2, "娜雅": 1, "莫里斯": 20, "黛安娜": 20, "芈芈": 25}}